{"_default": {}, "history": {"1": {"status": "non-completed", "command": {"command": "ON"}, "id": 2, "time": "17:36:36"}, "2": {"status": "non-completed", "command": {"command": "D358"}, "id": 3, "time": "17:36:45"}, "3": {"status": "non-completed", "command": {"command": "D359"}, "id": 4, "time": "17:39:43"}, "4": {"status": "non-completed", "command": {"command": "D359"}, "id": 5, "time": "17:39:47"}, "5": {"status": "non-completed", "command": {"command": "D3"}, "id": 6, "time": "17:39:51"}, "6": {"status": "non-completed", "command": {"command": "ON"}, "id": 7, "time": "17:42:25"}, "7": {"status": "non-completed", "command": {"command": "D3"}, "id": 8, "time": "17:42:30"}, "8": {"status": "non-completed", "command": {"command": "S"}, "id": 9, "time": "17:42:33"}, "9": {"status": "non-completed", "command": {"command": "R"}, "id": 10, "time": "17:42:35"}, "10": {"status": "non-completed", "command": {"command": "D358"}, "id": 11, "time": "17:42:37"}, "11": {"status": "completed", "command": {"command": "D3"}, "id": 12, "time": "17:43:47"}, "12": {"status": "completed", "command": {"command": "D3"}, "id": 13, "time": "17:45:58"}, "13": {"status": "non-completed", "command": {"command": "D354"}, "id": 14, "time": "17:46:06"}, "14": {"status": "non-completed", "command": {"command": "D358"}, "id": 15, "time": "18:08:22"}, "15": {"status": "non-completed", "command": {"command": "D358"}, "id": 16, "time": "18:08:26"}, "16": {"status": "non-completed", "command": {"command": "ON"}, "id": 17, "time": "18:08:28"}, "17": {"status": "non-completed", "command": {"command": "D358"}, "id": 18, "time": "18:08:33"}, "18": {"status": "completed", "command": {"command": "D2"}, "id": 19, "time": "18:08:47"}, "19": {"status": "completed", "command": {"command": "D200"}, "id": 20, "time": "18:10:55"}, "20": {"status": "non-completed", "command": {"command": "H"}, "id": 21, "time": "18:12:13"}, "21": {"status": "non-completed", "command": {"command": "H"}, "id": 22, "time": "18:12:19"}, "22": {"status": "non-completed", "command": {"command": "ON"}, "id": 23, "time": "18:14:08"}, "23": {"status": "completed", "command": {"command": "H"}, "id": 24, "time": "18:14:27"}, "24": {"status": "completed", "command": {"command": "SZ"}, "id": 25, "time": "18:14:49"}, "25": {"status": "completed", "command": {"command": "D5"}, "id": 26, "time": "18:15:00"}, "26": {"status": "completed", "command": {"command": "SZ"}, "id": 27, "time": "18:16:21"}, "27": {"status": "non-completed", "command": {"command": "SZ"}, "id": 28, "time": "18:16:23"}, "28": {"status": "completed", "command": {"command": "D5"}, "id": 29, "time": "18:16:25"}, "29": {"status": "completed", "command": {"command": "SZ"}, "id": 30, "time": "18:16:29"}}}